[
  {
    "inputs": [
      {
        "internalType": "address",
        "name": "_faucet",
        "type": "address"
      }
    ],
    "stateMutability": "nonpayable",
    "type": "constructor"
  },
  {
    "anonymous": false,
    "inputs": [
      {
        "indexed": true,
        "internalType": "address",
        "name": "oldFaucet",
        "type": "address"
      },
      {
        "indexed": true,
        "internalType": "address",
        "name": "newFaucet",
        "type": "address"
      }
    ],
    "name": "FaucetUpdated",
    "type": "event"
  },
  {
    "anonymous": false,
    "inputs": [
      {
        "indexed": false,
        "internalType": "uint256",
        "name": "totalRequests",
        "type": "uint256"
      },
      {
        "indexed": false,
        "internalType": "uint256",
        "name": "totalDistributed",
        "type": "uint256"
      },
      {
        "indexed": false,
        "internalType": "uint256",
        "name": "uniqueUsers",
        "type": "uint256"
      }
    ],
    "name": "GlobalStatsUpdated",
    "type": "event"
  },
  {
    "anonymous": false,
    "inputs": [
      {
        "indexed": true,
        "internalType": "address",
        "name": "user",
        "type": "address"
      },
      {
        "indexed": false,
        "internalType": "uint256",
        "name": "amount",
        "type": "uint256"
      },
      {
        "indexed": false,
        "internalType": "uint256",
        "name": "requestCount",
        "type": "uint256"
      },
      {
        "indexed": false,
        "internalType": "uint256",
        "name": "totalDistributed",
        "type": "uint256"
      }
    ],
    "name": "StatsRecorded",
    "type": "event"
  },
  {
    "anonymous": false,
    "inputs": [
      {
        "indexed": true,
        "internalType": "address",
        "name": "admin",
        "type": "address"
      },
      {
        "indexed": false,
        "internalType": "uint256",
        "name": "timestamp",
        "type": "uint256"
      }
    ],
    "name": "StatsReset",
    "type": "event"
  },
  {
    "inputs": [],
    "name": "faucet",
    "outputs": [
      {
        "internalType": "address",
        "name": "",
        "type": "address"
      }
    ],
    "stateMutability": "view",
    "type": "function"
  },
  {
    "inputs": [],
    "name": "getAverageRequestAmount",
    "outputs": [
      {
        "internalType": "uint256",
        "name": "average",
        "type": "uint256"
      }
    ],
    "stateMutability": "view",
    "type": "function"
  },
  {
    "inputs": [],
    "name": "getGlobalStats",
    "outputs": [
      {
        "components": [
          {
            "internalType": "uint256",
            "name": "totalRequests",
            "type": "uint256"
          },
          {
            "internalType": "uint256",
            "name": "totalDistributed",
            "type": "uint256"
          },
          {
            "internalType": "uint256",
            "name": "uniqueUsers",
            "type": "uint256"
          },
          {
            "internalType": "uint256",
            "name": "lastUpdateTime",
            "type": "uint256"
          }
        ],
        "internalType": "struct FaucetStats.GlobalStats",
        "name": "stats",
        "type": "tuple"
      }
    ],
    "stateMutability": "view",
    "type": "function"
  },
  {
    "inputs": [],
    "name": "getTotalDistributed",
    "outputs": [
      {
        "internalType": "uint256",
        "name": "total",
        "type": "uint256"
      }
    ],
    "stateMutability": "view",
    "type": "function"
  },
  {
    "inputs": [],
    "name": "getTotalRequests",
    "outputs": [
      {
        "internalType": "uint256",
        "name": "total",
        "type": "uint256"
      }
    ],
    "stateMutability": "view",
    "type": "function"
  },
  {
    "inputs": [],
    "name": "getUniqueUsers",
    "outputs": [
      {
        "internalType": "uint256",
        "name": "count",
        "type": "uint256"
      }
    ],
    "stateMutability": "view",
    "type": "function"
  },
  {
    "inputs": [
      {
        "internalType": "address",
        "name": "user",
        "type": "address"
      }
    ],
    "name": "getUserAverageRequest",
    "outputs": [
      {
        "internalType": "uint256",
        "name": "average",
        "type": "uint256"
      }
    ],
    "stateMutability": "view",
    "type": "function"
  },
  {
    "inputs": [
      {
        "internalType": "address",
        "name": "user",
        "type": "address"
      }
    ],
    "name": "getUserLargestRequest",
    "outputs": [
      {
        "internalType": "uint256",
        "name": "amount",
        "type": "uint256"
      }
    ],
    "stateMutability": "view",
    "type": "function"
  },
  {
    "inputs": [
      {
        "internalType": "address",
        "name": "user",
        "type": "address"
      }
    ],
    "name": "getUserReport",
    "outputs": [
      {
        "internalType": "uint256",
        "name": "requestCount",
        "type": "uint256"
      },
      {
        "internalType": "uint256",
        "name": "totalReceived",
        "type": "uint256"
      },
      {
        "internalType": "uint256",
        "name": "averageAmount",
        "type": "uint256"
      },
      {
        "internalType": "uint256",
        "name": "largestAmount",
        "type": "uint256"
      },
      {
        "internalType": "uint256",
        "name": "daysSinceFirst",
        "type": "uint256"
      }
    ],
    "stateMutability": "view",
    "type": "function"
  },
  {
    "inputs": [
      {
        "internalType": "address",
        "name": "user",
        "type": "address"
      }
    ],
    "name": "getUserRequestCount",
    "outputs": [
      {
        "internalType": "uint256",
        "name": "count",
        "type": "uint256"
      }
    ],
    "stateMutability": "view",
    "type": "function"
  },
  {
    "inputs": [
      {
        "internalType": "address",
        "name": "user",
        "type": "address"
      }
    ],
    "name": "getUserStats",
    "outputs": [
      {
        "components": [
          {
            "internalType": "uint256",
            "name": "requestCount",
            "type": "uint256"
          },
          {
            "internalType": "uint256",
            "name": "totalReceived",
            "type": "uint256"
          },
          {
            "internalType": "uint256",
            "name": "firstRequestTime",
            "type": "uint256"
          },
          {
            "internalType": "uint256",
            "name": "lastRequestTime",
            "type": "uint256"
          },
          {
            "internalType": "uint256",
            "name": "largestRequest",
            "type": "uint256"
          },
          {
            "internalType": "uint256",
            "name": "averageRequest",
            "type": "uint256"
          }
        ],
        "internalType": "struct FaucetStats.UserStats",
        "name": "stats",
        "type": "tuple"
      }
    ],
    "stateMutability": "view",
    "type": "function"
  },
  {
    "inputs": [
      {
        "internalType": "address",
        "name": "user",
        "type": "address"
      }
    ],
    "name": "getUserTimeframe",
    "outputs": [
      {
        "internalType": "uint256",
        "name": "firstRequest",
        "type": "uint256"
      },
      {
        "internalType": "uint256",
        "name": "lastRequest",
        "type": "uint256"
      }
    ],
    "stateMutability": "view",
    "type": "function"
  },
  {
    "inputs": [
      {
        "internalType": "address",
        "name": "user",
        "type": "address"
      }
    ],
    "name": "getUserTotalReceived",
    "outputs": [
      {
        "internalType": "uint256",
        "name": "total",
        "type": "uint256"
      }
    ],
    "stateMutability": "view",
    "type": "function"
  },
  {
    "inputs": [],
    "name": "globalStats",
    "outputs": [
      {
        "internalType": "uint256",
        "name": "totalRequests",
        "type": "uint256"
      },
      {
        "internalType": "uint256",
        "name": "totalDistributed",
        "type": "uint256"
      },
      {
        "internalType": "uint256",
        "name": "uniqueUsers",
        "type": "uint256"
      },
      {
        "internalType": "uint256",
        "name": "lastUpdateTime",
        "type": "uint256"
      }
    ],
    "stateMutability": "view",
    "type": "function"
  },
  {
    "inputs": [
      {
        "internalType": "address",
        "name": "user",
        "type": "address"
      }
    ],
    "name": "hasUserRequested",
    "outputs": [
      {
        "internalType": "bool",
        "name": "requested",
        "type": "bool"
      }
    ],
    "stateMutability": "view",
    "type": "function"
  },
  {
    "inputs": [
      {
        "internalType": "address",
        "name": "user",
        "type": "address"
      },
      {
        "internalType": "uint256",
        "name": "amount",
        "type": "uint256"
      },
      {
        "internalType": "bool",
        "name": "isFirstTime",
        "type": "bool"
      }
    ],
    "name": "recordRequest",
    "outputs": [],
    "stateMutability": "nonpayable",
    "type": "function"
  },
  {
    "inputs": [],
    "name": "resetStats",
    "outputs": [],
    "stateMutability": "nonpayable",
    "type": "function"
  },
  {
    "inputs": [
      {
        "internalType": "address",
        "name": "newFaucet",
        "type": "address"
      }
    ],
    "name": "updateFaucet",
    "outputs": [],
    "stateMutability": "nonpayable",
    "type": "function"
  },
  {
    "inputs": [
      {
        "internalType": "address",
        "name": "",
        "type": "address"
      }
    ],
    "name": "userStats",
    "outputs": [
      {
        "internalType": "uint256",
        "name": "requestCount",
        "type": "uint256"
      },
      {
        "internalType": "uint256",
        "name": "totalReceived",
        "type": "uint256"
      },
      {
        "internalType": "uint256",
        "name": "firstRequestTime",
        "type": "uint256"
      },
      {
        "internalType": "uint256",
        "name": "lastRequestTime",
        "type": "uint256"
      },
      {
        "internalType": "uint256",
        "name": "largestRequest",
        "type": "uint256"
      },
      {
        "internalType": "uint256",
        "name": "averageRequest",
        "type": "uint256"
      }
    ],
    "stateMutability": "view",
    "type": "function"
  }
]
